pyproteinsext/.gitignore
pyproteinsext/LICENSE
pyproteinsext/__init__.py
pyproteinsext/__main__.py
pyproteinsext/annotators.py
pyproteinsext/biogrid.py
pyproteinsext/ena.py
pyproteinsext/fastaContainerFactory.py
pyproteinsext/hmmrContainerFactory.py
pyproteinsext/matrisome.py
pyproteinsext/ontology.py
pyproteinsext/pfam.py
pyproteinsext/pfamCutter.py
pyproteinsext/proteinContainer.py
pyproteinsext/psicquic.py
pyproteinsext/refseq.py
pyproteinsext/setup.py
pyproteinsext/tmhmmContainerFactory.py
pyproteinsext/topology.py
pyproteinsext/uniprot.py
pyproteinsext/uniprotAnnotator.py
pyproteinsext/database/__init__.py
pyproteinsext/database/uniprotFastaFS.py
pyproteinsext/notebooks/HMMR_wrapper.ipynb
pyproteinsext/notebooks/psicquic_demo.ipynb
pyproteinsext/notebooks/uniprotWrapper.ipynb
pyproteinsext/notebooks/.ipynb_checkpoints/HMMR_wrapper-checkpoint.ipynb
pyproteinsext/notebooks/.ipynb_checkpoints/uniprotWrapper-checkpoint.ipynb
pyproteinsext/notebooks/data/example_hmmscan.out.gz
pyproteinsext/services/uniprot/__init__.py
pyproteinsext/services/uniprot/collectionProxy.py
pyproteinsext/services/uniprot/entryProxy.py
pyproteinsext/services/uniprot/redisClient.py
pyproteinsext-3.1.6.dist-info/METADATA
pyproteinsext-3.1.6.dist-info/WHEEL
pyproteinsext-3.1.6.dist-info/licenses/LICENSE
pyproteinsext-3.1.6.dist-info/RECORD
