Metadata-Version: 2.3
Name: pyproteinsext
Version: 3.1.6
Summary: 'Extending pyproteins for bioinformatics tools&services'
Requires-Python: >=3.9
Requires-Dist: biopython>=1.79
Requires-Dist: bs4>=0.0.1
Requires-Dist: pyproteins>=2.1.1
